gymxq/__init__.py
gymxq/constants.py
gymxq/utils.py
gymxq/envs/__init__.py
gymxq/envs/game.py
gymxq/envs/xiangqi.py
gymxq/resources/bA.png
gymxq/resources/bB.png
gymxq/resources/bC.png
gymxq/resources/bK.png
gymxq/resources/bN.png
gymxq/resources/bP.png
gymxq/resources/bR.png
gymxq/resources/board540x600.png
gymxq/resources/cross.png
gymxq/resources/frame.png
gymxq/resources/icon.ico
gymxq/resources/rA.png
gymxq/resources/rB.png
gymxq/resources/rC.png
gymxq/resources/rK.png
gymxq/resources/rN.png
gymxq/resources/rP.png
gymxq/resources/rR.png
gymxq-1.1.0.dist-info/LICENSE
gymxq-1.1.0.dist-info/METADATA
gymxq-1.1.0.dist-info/WHEEL
gymxq-1.1.0.dist-info/top_level.txt
gymxq-1.1.0.dist-info/RECORD
