Metadata-Version: 2.1
Name: gymxq
Version: 1.1.0
License-File: LICENSE
Requires-Dist: cppxq (>=1.0.0)
Requires-Dist: gymnasium (>=0.27.0)
Requires-Dist: pygame (>=2.1.2)
Requires-Dist: moviepy (>=1.0.3)
Requires-Dist: termcolor (>=2.2.0)
Requires-Dist: pytest (>=7.1.3)
